odoo/addons/sale_manual_delivery/README.rst
odoo/addons/sale_manual_delivery/__init__.py
odoo/addons/sale_manual_delivery/__manifest__.py
odoo/addons/sale_manual_delivery/hook.py
odoo/addons/sale_manual_delivery/i18n/es.po
odoo/addons/sale_manual_delivery/i18n/it.po
odoo/addons/sale_manual_delivery/i18n/sale_manual_delivery.pot
odoo/addons/sale_manual_delivery/models/__init__.py
odoo/addons/sale_manual_delivery/models/crm_team.py
odoo/addons/sale_manual_delivery/models/procurement_group.py
odoo/addons/sale_manual_delivery/models/sale_order.py
odoo/addons/sale_manual_delivery/models/sale_order_line.py
odoo/addons/sale_manual_delivery/models/stock_move.py
odoo/addons/sale_manual_delivery/readme/CONTRIBUTORS.md
odoo/addons/sale_manual_delivery/readme/CREDITS.md
odoo/addons/sale_manual_delivery/readme/DESCRIPTION.md
odoo/addons/sale_manual_delivery/security/ir.model.access.csv
odoo/addons/sale_manual_delivery/static/description/field.png
odoo/addons/sale_manual_delivery/static/description/icon.png
odoo/addons/sale_manual_delivery/static/description/icon.svg
odoo/addons/sale_manual_delivery/static/description/index.html
odoo/addons/sale_manual_delivery/static/description/wizard.png
odoo/addons/sale_manual_delivery/tests/__init__.py
odoo/addons/sale_manual_delivery/tests/test_manual_delivery.py
odoo/addons/sale_manual_delivery/views/crm_team.xml
odoo/addons/sale_manual_delivery/views/sale_order.xml
odoo/addons/sale_manual_delivery/wizard/__init__.py
odoo/addons/sale_manual_delivery/wizard/manual_delivery.py
odoo/addons/sale_manual_delivery/wizard/manual_delivery.xml
odoo/addons/sale_manual_delivery/wizard/manual_delivery_line.py
odoo_addon_sale_manual_delivery-18.0.1.0.1.dist-info/METADATA
odoo_addon_sale_manual_delivery-18.0.1.0.1.dist-info/WHEEL
odoo_addon_sale_manual_delivery-18.0.1.0.1.dist-info/top_level.txt
odoo_addon_sale_manual_delivery-18.0.1.0.1.dist-info/RECORD
